[
	{"author_tz_offset":"510","num_authors":"6","num_commits":"29"},
	{"author_tz_offset":"-119","num_authors":"3","num_commits":"47"},
	{"author_tz_offset":"-570","num_authors":"5","num_commits":"61"},
	{"author_tz_offset":"2","num_authors":"2","num_commits":"75"},
	{"author_tz_offset":"840","num_authors":"40","num_commits":"77"},
	{"author_tz_offset":"-780","num_authors":"4","num_commits":"115"},
	{"author_tz_offset":"410","num_authors":"1","num_commits":"222"},
	{"author_tz_offset":"539","num_authors":"4","num_commits":"239"},
	{"author_tz_offset":"-660","num_authors":"66","num_commits":"665"},
	{"author_tz_offset":"-720","num_authors":"66","num_commits":"676"},
	{"author_tz_offset":"119","num_authors":"24","num_commits":"738"},
	{"author_tz_offset":"59","num_authors":"16","num_commits":"823"},
	{"author_tz_offset":"350","num_authors":"20","num_commits":"852"},
	{"author_tz_offset":"-330","num_authors":"69","num_commits":"2,411"},
	{"author_tz_offset":"390","num_authors":"400","num_commits":"10,522"},
	{"author_tz_offset":"-210","num_authors":"228","num_commits":"11,177"},
	{"author_tz_offset":"-60","num_authors":"336","num_commits":"13,115"},
	{"author_tz_offset":"-540","num_authors":"533","num_commits":"15,412"},
	{"author_tz_offset":"-150","num_authors":"261","num_commits":"17,631"},
	{"author_tz_offset":"345","num_authors":"1,493","num_commits":"46,666"},
	{"author_tz_offset":"630","num_authors":"1,462","num_commits":"57,239"},
	{"author_tz_offset":"570","num_authors":"1,831","num_commits":"77,404"},
	{"author_tz_offset":"270","num_authors":"3,217","num_commits":"80,551"},
	{"author_tz_offset":"210","num_authors":"2,934","num_commits":"84,187"},
	{"author_tz_offset":"-270","num_authors":"3,364","num_commits":"100,352"},
	{"author_tz_offset":"-600","num_authors":"2,862","num_commits":"114,928"},
	{"author_tz_offset":"300","num_authors":"8,756","num_commits":"261,919"},
	{"author_tz_offset":"780","num_authors":"7,752","num_commits":"346,255"},
	{"author_tz_offset":"360","num_authors":"10,612","num_commits":"353,635"},
	{"author_tz_offset":"720","num_authors":"8,137","num_commits":"356,394"},
	{"author_tz_offset":"-120","num_authors":"25,172","num_commits":"601,120"},
	{"author_tz_offset":"420","num_authors":"32,910","num_commits":"977,037"},
	{"author_tz_offset":"660","num_authors":"19,595","num_commits":"987,197"},
	{"author_tz_offset":"240","num_authors":"28,064","num_commits":"1,323,546"},
	{"author_tz_offset":"600","num_authors":"28,801","num_commits":"1,596,047"},
	{"author_tz_offset":"330","num_authors":"65,587","num_commits":"2,134,972"},
	{"author_tz_offset":"-180","num_authors":"78,039","num_commits":"2,569,200"},
	{"author_tz_offset":"540","num_authors":"60,650","num_commits":"3,593,108"},
	{"author_tz_offset":"-360","num_authors":"111,466","num_commits":"4,310,574"},
	{"author_tz_offset":"180","num_authors":"133,436","num_commits":"5,297,739"},
	{"author_tz_offset":"-480","num_authors":"237,964","num_commits":"6,546,453"},
	{"author_tz_offset":"480","num_authors":"218,978","num_commits":"6,986,451"},
	{"author_tz_offset":"-300","num_authors":"281,626","num_commits":"11,261,945"},
	{"author_tz_offset":"-240","num_authors":"252,337","num_commits":"12,264,600"},
	{"author_tz_offset":"-420","num_authors":"363,523","num_commits":"12,942,089"},
	{"author_tz_offset":"60","num_authors":"404,008","num_commits":"21,112,787"},
	{"author_tz_offset":"120","num_authors":"422,586","num_commits":"24,795,246"},
	{"author_tz_offset":"0","num_authors":"262,201","num_commits":"34,793,750"}
]